datasets/__init__.py
datasets/_datasets_loader.py
fairbalance/__init__.py
fairbalance/_tools/__init__.py
fairbalance/_tools/_fairness_analysis.py
fairbalance/_tools/_mitigator.py
fairbalance/_tools/_processor.py
fairbalance/_tools/_utils.py
fairbalance/_tools/tests/__init__.py
fairbalance/_tools/tests/test_fairness_analysis.py
fairbalance/_tools/tests/test_mitigator.py
fairbalance/_tools/tests/test_processor.py
fairbalance/_tools/tests/test_utils.py
fairbalance/datasets/__init__.py
fairbalance/datasets/_datasets_constants.py
fairbalance/datasets/_datasets_loader.py
fairbalance/metrics/__init__.py
fairbalance/metrics/_dataset_metrics.py
fairbalance/metrics/_fairness_analysis.py
fairbalance/metrics/_model_metrics.py
fairbalance/metrics/tests/__init__.py
fairbalance/metrics/tests/test_dataset_metrics.py
fairbalance/metrics/tests/test_fairness_analysis.py
fairbalance/metrics/tests/test_model_metrics.py
fairbalance/mitigation_strategies/__init__.py
fairbalance/mitigation_strategies/_mitigation_strategies.py
fairbalance/mitigation_strategies/base.py
fairbalance/processors/__init__.py
fairbalance/processors/_processors.py
fairbalance/processors/base.py
fairbalance/tests/__init__.py
fairbalance/tests/base_test.py
fairbalance/tests/test_common.py
fairbalance/tests/test_template.py
fairbalance/tools/__init__.py
fairbalance/tools/_fairness_analysis.py
fairbalance/tools/_mitigator.py
fairbalance/tools/_processor.py
fairbalance/tools/_utils.py
fairbalance/tools/tests/__init__.py
fairbalance/tools/tests/test_fairness_analysis.py
fairbalance/tools/tests/test_mitigator.py
fairbalance/tools/tests/test_processor.py
fairbalance/tools/tests/test_utils.py
fairbalance/utils/__init__.py
fairbalance/utils/_balanced_train_test_split.py
fairbalance/utils/discovery.py
fairbalance/utils/tests/__init__.py
fairbalance/utils/tests/_method_selection.py
fairbalance/utils/tests/_pipeline.py
fairbalance/utils/tests/test_balanced_train_test_split.py
metrics/__init__.py
metrics/_dataset_metrics.py
fairbalance-0.1.20.dist-info/METADATA
fairbalance-0.1.20.dist-info/WHEEL
fairbalance-0.1.20.dist-info/top_level.txt
fairbalance-0.1.20.dist-info/RECORD
